README.md
setup.py
atd_datautil.egg-info/PKG-INFO
atd_datautil.egg-info/SOURCES.txt
atd_datautil.egg-info/dependency_links.txt
atd_datautil.egg-info/requires.txt
atd_datautil.egg-info/top_level.txt
datautil/__init__.py
datautil/datautil.py