Metadata-Version: 2.1
Name: atd-datautil
Version: 0.0.2
Summary: Miscellaneous utilities for manipulating data.
Home-page: https://github.com/cityofaustin/atd-utils-data
Author: City of Austin
Author-email: transportation.data@austintexas.gov
License: UNKNOWN
Platform: UNKNOWN
Classifier: Programming Language :: Python :: 3
Classifier: License :: Public Domain
Classifier: Operating System :: OS Independent
Classifier: Development Status :: 4 - Beta
